odoo/addons/pms_housekeeping/README.rst
odoo/addons/pms_housekeeping/__init__.py
odoo/addons/pms_housekeeping/__manifest__.py
odoo/addons/pms_housekeeping/data/cron_jobs.xml
odoo/addons/pms_housekeeping/data/pms_housekeeping_data.xml
odoo/addons/pms_housekeeping/i18n/es.po
odoo/addons/pms_housekeeping/i18n/it.po
odoo/addons/pms_housekeeping/i18n/pms_housekeeping.pot
odoo/addons/pms_housekeeping/models/__init__.py
odoo/addons/pms_housekeeping/models/hr_employee.py
odoo/addons/pms_housekeeping/models/pms_housekeeping_cancellation_type.py
odoo/addons/pms_housekeeping/models/pms_housekeeping_task.py
odoo/addons/pms_housekeeping/models/pms_housekeeping_task_type.py
odoo/addons/pms_housekeeping/models/pms_room.py
odoo/addons/pms_housekeeping/readme/CONTRIBUTORS.rst
odoo/addons/pms_housekeeping/readme/DESCRIPTION.rst
odoo/addons/pms_housekeeping/security/ir.model.access.csv
odoo/addons/pms_housekeeping/static/description/icon.png
odoo/addons/pms_housekeeping/static/description/index.html
odoo/addons/pms_housekeeping/tests/__init__.py
odoo/addons/pms_housekeeping/tests/common.py
odoo/addons/pms_housekeeping/tests/test_pms_housekeeping_task.py
odoo/addons/pms_housekeeping/tests/test_pms_housekeeping_task_type.py
odoo/addons/pms_housekeeping/tests/test_pms_hr_employee.py
odoo/addons/pms_housekeeping/views/hr_employee_views.xml
odoo/addons/pms_housekeeping/views/pms_housekeeping_task_type_views.xml
odoo/addons/pms_housekeeping/views/pms_housekeeping_task_views.xml
odoo/addons/pms_housekeeping/views/pms_housekeeping_views.xml
odoo/addons/pms_housekeeping/views/pms_room_views.xml
odoo14_addon_pms_housekeeping-14.0.1.0.2.dev25.dist-info/METADATA
odoo14_addon_pms_housekeeping-14.0.1.0.2.dev25.dist-info/WHEEL
odoo14_addon_pms_housekeeping-14.0.1.0.2.dev25.dist-info/top_level.txt
odoo14_addon_pms_housekeeping-14.0.1.0.2.dev25.dist-info/RECORD
